chalos/__init__.py
chalos/cli.py
chalos-0.1.0.dist-info/licenses/LICENSE
chalos-0.1.0.dist-info/METADATA
chalos-0.1.0.dist-info/WHEEL
chalos-0.1.0.dist-info/entry_points.txt
chalos-0.1.0.dist-info/top_level.txt
chalos-0.1.0.dist-info/RECORD
