Metadata-Version: 2.4
Name: chalos
Version: 0.1.0
Summary: Order Chalos empanadas, burritos, sandwiches, and coffee from the CLI. Real hackers order Chalos from the CLI.
Author: William
Keywords: cli,chalos,empanadas,San Francisco
Classifier: Programming Language :: Python :: 3
Classifier: Programming Language :: Python :: 3 :: Only
Classifier: Programming Language :: Python :: 3.9
Classifier: Programming Language :: Python :: 3.10
Classifier: Programming Language :: Python :: 3.11
Classifier: Programming Language :: Python :: 3.12
Classifier: License :: OSI Approved :: MIT License
Classifier: Operating System :: OS Independent
Requires-Python: >=3.8
License-File: LICENSE
Dynamic: license-file
